cleanvoice/__init__.py
cleanvoice/cleanvoice.py
cleanvoice/client.py
cleanvoice/file_handler.py
cleanvoice/types.py
cleanvoice_sdk-1.0.1.dist-info/licenses/LICENSE
cleanvoice_sdk-1.0.1.dist-info/METADATA
cleanvoice_sdk-1.0.1.dist-info/WHEEL
cleanvoice_sdk-1.0.1.dist-info/top_level.txt
cleanvoice_sdk-1.0.1.dist-info/RECORD
