Metadata-Version: 2.4
Name: cleanvoice-sdk
Version: 1.0.1
Summary: Official Python SDK for Cleanvoice AI audio processing
Author-email: Cleanvoice AI <support@cleanvoice.ai>
License: MIT
Project-URL: Homepage, https://cleanvoice.ai
Project-URL: Documentation, https://docs.cleanvoice.ai
Project-URL: Repository, https://github.com/cleanvoice/cleanvoice-python
Project-URL: Bug Tracker, https://github.com/cleanvoice/cleanvoice-python/issues
Keywords: cleanvoice,audio,processing,ai,clean
Classifier: Development Status :: 4 - Beta
Classifier: Intended Audience :: Developers
Classifier: License :: OSI Approved :: MIT License
Classifier: Programming Language :: Python :: 3
Classifier: Programming Language :: Python :: 3.8
Classifier: Programming Language :: Python :: 3.9
Classifier: Programming Language :: Python :: 3.10
Classifier: Programming Language :: Python :: 3.11
Classifier: Programming Language :: Python :: 3.12
Classifier: Topic :: Software Development :: Libraries :: Python Modules
Classifier: Topic :: Multimedia :: Sound/Audio :: Analysis
Requires-Python: >=3.8
License-File: LICENSE
Requires-Dist: requests>=2.25.0
Requires-Dist: pydantic>=2.0.0
Requires-Dist: typing-extensions>=4.0.0
Requires-Dist: soundfile>=0.12.0
Requires-Dist: librosa>=0.10.0
Requires-Dist: mutagen>=1.45.0
Requires-Dist: av>=10.0.0
Provides-Extra: dev
Requires-Dist: pytest>=7.0.0; extra == "dev"
Requires-Dist: pytest-cov>=4.0.0; extra == "dev"
Requires-Dist: black>=22.0.0; extra == "dev"
Requires-Dist: isort>=5.10.0; extra == "dev"
Requires-Dist: flake8>=4.0.0; extra == "dev"
Requires-Dist: mypy>=1.0.0; extra == "dev"
Requires-Dist: types-requests>=2.25.0; extra == "dev"
Dynamic: license-file
